d3m_interface/__init__.py
d3m_interface/automl_interface.py
d3m_interface/confidence_calculator.py
d3m_interface/data_converter.py
d3m_interface/grpc_client.py
d3m_interface/pipeline.py
d3m_interface/utils.py
d3m_interface/visualization.py
d3m_interface/resource/primitives_metadata.json
d3m_interface-0.9.0.dist-info/LICENSE.txt
d3m_interface-0.9.0.dist-info/METADATA
d3m_interface-0.9.0.dist-info/NOTICE.txt
d3m_interface-0.9.0.dist-info/WHEEL
d3m_interface-0.9.0.dist-info/top_level.txt
d3m_interface-0.9.0.dist-info/RECORD
