Metadata-Version: 2.1
Name: d3m-interface
Version: 0.9.0
Summary: Library to use D3M AutoML Systems
Home-page: https://gitlab.com/ViDA-NYU/d3m/d3m_interface
Author: Roque Lopez, Remi Rampin, Sonia Castelo
Author-email: rlopez@nyu.edu, remi.rampin@nyu.edu, s.castelo@nyu.edu
Maintainer: Roque Lopez, Remi Rampin
Maintainer-email: rlopez@nyu.edu, remi.rampin@nyu.edu
License: Apache-2.0
Platform: UNKNOWN
Classifier: Programming Language :: Python :: 3
Classifier: License :: OSI Approved :: Apache Software License
Classifier: Operating System :: OS Independent
Requires-Python: >=3.6
License-File: LICENSE.txt
License-File: NOTICE.txt
Requires-Dist: d3m
Requires-Dist: d3m-automl-rpc
Requires-Dist: pandas (<=1.3.4,>=1.1.3)
Requires-Dist: numpy
Requires-Dist: scikit-learn
Requires-Dist: lime (<0.3,>=0.2)
Requires-Dist: pipelineprofiler (<2,>=0.1)
Requires-Dist: datamart-profiler (>=0.9)
Requires-Dist: data-profile-viewer (<3,>=0.2.7)
Requires-Dist: visual-text-explorer (<2,>=0.1)
